extratools_av/__init__.py
extratools_av/py.typed
extratools_av/audio/__init__.py
extratools_av/video/__init__.py
extratools_av-0.1.0.dist-info/METADATA
extratools_av-0.1.0.dist-info/WHEEL
extratools_av-0.1.0.dist-info/licenses/LICENSE
extratools_av-0.1.0.dist-info/RECORD
