Metadata-Version: 2.4
Name: extratools-av
Version: 0.1.0
Project-URL: Repository, https://github.com/chuanconggao/extratools-av
Author-email: Chuancong Gao <chuanconggao@users.noreply.github.com>
License-Expression: MIT
License-File: LICENSE
Requires-Python: >=3.11
Requires-Dist: moviepy>=2.1.2
